<?xml version="1.0" encoding="UTF-8"?>
<addon
  id="skin.rapier"
  version="3.06"
  name="Rapier"
  provider-name="Scarfa">
  <requires>
    <import addon="xbmc.gui" version="2.11"/>
  </requires>
  <extension 
    point="xbmc.gui.skin"
    defaultresolution="720p" 
    defaultresolutionwide="720p"
    defaultthemename="textures.xbt" 
    effectslowdown="0.75"
    debugging="false"/>
  <extension  point="xbmc.addon.metadata">
    <summary>Rapier skin by scarfa</summary>
    <description>The goal is to provide a simple but elegant interface that emphasizes efficiency when browsing your media. Important considerations are put on usability, performance, and providing the user with flexibility when it comes to customization. Rapier supports the latest XBMC features and new ones will be added in the future as long as it fits in with Rapier's design goals.</description>
    <platform>all</platform>
  </extension>
</addon>
